lineup_optimizer/__init__.py
lineup_optimizer/exceptions.py
lineup_optimizer/lineup.py
lineup_optimizer/lineup_builder.py
lineup_optimizer/lineup_builder_slot.py
lineup_optimizer/lineup_tag_rules.py
lineup_optimizer/tags_controller.py
lineup_optimizer/exporter/__init__.py
lineup_optimizer/exporter/exporter.py
lineup_optimizer/parsers/__init__.py
lineup_optimizer/parsers/draftkings_parser.py
lineup_optimizer/parsers/fanduel_parser.py
lineup_optimizer/parsers/yahoo_parser.py
lineup_optimizer/settings/__init__.py
lineup_optimizer/settings/default_settings.py
lineup_optimizer/settings/draftkings_settings.py
lineup_optimizer/settings/fanduel_settings.py
lineup_optimizer/settings/yahoo_settings.py
lineup_optimizer-0.0.3.dist-info/METADATA
lineup_optimizer-0.0.3.dist-info/WHEEL
lineup_optimizer-0.0.3.dist-info/licenses/LICENSE
lineup_optimizer-0.0.3.dist-info/RECORD
