Metadata-Version: 2.1
Name: lineup_optimizer
Version: 0.0.3
Summary: A Python package for optimizing and generating DFS lineups.
Project-URL: Homepage, https://github.com/n-roth12/DFSLineupOptimizer
Author: Nolan Roth
License-File: LICENSE
Classifier: License :: OSI Approved :: MIT License
Classifier: Operating System :: OS Independent
Classifier: Programming Language :: Python :: 3
Requires-Python: >=3.7
